retinaface/__init__.py
retinaface/checks.py
retinaface/postprocess.py
retinaface/preprocess.py
retinaface/types.py
retinaface/utils.py
retinaface/weights.py
tiny_retinaface-0.1.0.dist-info/licenses/LICENSE
tiny_retinaface-0.1.0.dist-info/METADATA
tiny_retinaface-0.1.0.dist-info/WHEEL
tiny_retinaface-0.1.0.dist-info/top_level.txt
tiny_retinaface-0.1.0.dist-info/RECORD
