Metadata-Version: 2.4
Name: tiny-retinaface
Version: 0.1.0
Summary: A fast and simplified implementation of biubug6/Pytorch_Retinaface inference module
Author-email: Davi A D Fabbro <fabda01@gmail.com>
License-Expression: MIT
Project-URL: Homepage, https://github.com/ddfabbro/tiny-retinaface
Keywords: face-detection,retinaface
Classifier: Programming Language :: Python :: 3
Requires-Python: >=3.9
License-File: LICENSE
Requires-Dist: numpy
Requires-Dist: opencv-python
Requires-Dist: onnxruntime
Provides-Extra: dev
Requires-Dist: pytest; extra == "dev"
Requires-Dist: pytest-cov; extra == "dev"
Requires-Dist: ruff; extra == "dev"
Dynamic: license-file
